{
  "friendly_name": "Black Arch",
  "image_src": "Black.png",
  "description": "BlackArch Linux is an Arch Linux-based penetration testing distribution for penetration testers and security researchers.",
  "name": "blackarchlinux/blackarch",
  "cores": 2,
  "memory": 2768,
  "gpu_count": 0,
  "cpu_allocation_method": "Inherit",
  "docker_registry": "https://index.docker.io/v1/",
  "categories": [
    "Development",
    "Desktop",
    "Security"
  ],
  "require_gpu": false,
  "enabled": true,
  "image_type": "Container",
  "architecture": [
    "amd64",
    "arm64"
  ]
}
